purse/__init__.py
purse/_meta.py
purse/aiotasks.py
purse/dataclasses.py
purse/datetime.py
purse/func.py
purse/imports.py
purse/json.py
purse/py.typed
purse/signals.py
purse/system.py
purse/telegram.py
purse/types.py
purse/typing.py
purse/waiter.py
purse/ext/__init__.py
purse/ext/aiogram/__init__.py
purse/ext/aiogram/decorators.py
purse/ext/aiogram/utils.py
purse/ext/aiogram/bootstrap/__init__.py
purse/ext/aiogram/bootstrap/bot.py
purse/ext/aiogram/bootstrap/commands.py
purse/ext/aiogram/bootstrap/polling.py
purse/ext/aiogram/bootstrap/webhook.py
purse/ext/aiogram/routers/__init__.py
purse/ext/aiogram/routers/errors.py
purse/ext/aiohttp/__init__.py
purse/ext/aiohttp/app.py
purse/ext/django/__init__.py
purse/ext/django/asgi.py
purse/ext/django/handlers.py
purse/ext/django/repo.py
purse/ext/django/wsgi.py
purse/http/__init__.py
purse/http/clients/__init__.py
purse/http/clients/base.py
purse/http/clients/httpx.py
purse/http/clients/pure.py
purse/http/clients/requests.py
purse/interfaces/__init__.py
purse/interfaces/protocols.py
purse/interfaces/repo/__init__.py
purse/interfaces/repo/memory.py
purse/logs/__init__.py
purse/logs/_internal.py
purse/logs/logconfig.py
purse/logs/telegram.py
python_purse-1.1.2.dist-info/METADATA
python_purse-1.1.2.dist-info/WHEEL
python_purse-1.1.2.dist-info/licenses/LICENSE
python_purse-1.1.2.dist-info/RECORD
