Metadata-Version: 2.4
Name: python-purse
Version: 1.1.2
Summary: Snippets and utils for python projects
Project-URL: Repository, https://github.com/andrei-samofalov/purse
Project-URL: Issues, https://github.com/andrei-samofalov/purse/issues
Author-email: Andrei Samofalov <andrei.e.samofalov@gmail.com>
License: Copyright 2025 Andrei Samofalov
License-File: LICENSE
Keywords: aiogram,aiohttp,logging,python,signals,snippets
Requires-Python: >=3.11
Provides-Extra: aiogram
Requires-Dist: aiogram>=3.17.0; extra == 'aiogram'
Provides-Extra: django
Requires-Dist: django>=5.1.5; extra == 'django'
